<?xml version="1.0" standalone="no"?>

<kickstart>


	<description>
	Your rabbitmq roll description here
	</description>

	<copyright>
	Copyright (c) 2000 - 2014 The Regents of the University of California.
	All rights reserved. Rocks(r) v6.1.1 www.rocksclusters.org
	
	</copyright>

	<changelog>
	$Log$
	</changelog>

	<package>foundation-python-rabbitmqclient</package>
	<package>foundation-python-pika</package>
	<package>foundation-python-tornado</package>
	<package>foundation-python-backports.ssl_match_hostname</package>
	<package>foundation-python-paramiko</package>
	<package>foundation-python-pycrypto</package>
	<package>erlang</package>
</kickstart>
